<courseRoster>
    <student>
        <firstName>Sydney</firstName>
        <lastName>Dean</lastName>
        <id>n105055c</id>
    </student>
    <student>
        <firstName>Ruby</firstName>
        <lastName>Howe</lastName>
        <id>n107907c</id>
    </student>
    <student>
        <firstName>Cash</firstName>
        <lastName>Griffin</lastName>
        <id>n104452c</id>
    </student>
	<student>
        <firstName>Mikayla</firstName>
        <lastName>Vaughn</lastName>
        <id>n104555c</id>
    </student>
	<student>
        <firstName>Jacquelyn</firstName>
        <lastName>Sellers</lastName>
        <id>n107474c</id>
    </student>
	<student>
        <firstName>Emily</firstName>
        <lastName>Morales</lastName>
        <id>n108536c</id>
    </student>
	<student>
        <firstName>Zaid</firstName>
        <lastName>Sims</lastName>
        <id>n109818c</id>
    </student>
	<student>
        <firstName>Sullivan</firstName>
        <lastName>Garza</lastName>
        <id>n103392c</id>
    </student>
	<student>
        <firstName>Brody</firstName>
        <lastName>Chambers</lastName>
        <id>n107364c</id>
    </student>
	<student>
        <firstName>Kaliyah</firstName>
        <lastName>Davenport</lastName>
        <id>n105959c</id>
    </student>
	<student>
        <firstName>Jabari</firstName>
        <lastName>Davis</lastName>
        <id>n103116c</id>
    </student>
	<student>
        <firstName>Rylee</firstName>
        <lastName>Ramos</lastName>
        <id>n108344c</id>
    </student>
	<student>
        <firstName>Mikaela</firstName>
        <lastName>Glenn</lastName>
        <id>n107662c</id>
    </student>
	<student>
        <firstName>Yesenia</firstName>
        <lastName>Carrillo</lastName>
        <id>n105619c</id>
    </student>
	<student>
        <firstName>Gustavo</firstName>
        <lastName>Walls</lastName>
        <id>n101857c</id>
    </student>
	<student>
        <firstName>Caitlin</firstName>
        <lastName>Green</lastName>
        <id>n109582c</id>
    </student>
	<student>
        <firstName>Lorelei</firstName>
        <lastName>Pratt</lastName>
        <id>n101325c</id>
    </student>
	<student>
        <firstName>Jovan</firstName>
        <lastName>Newman</lastName>
        <id>n107055c</id>
    </student>
	<student>
        <firstName>Deegan</firstName>
        <lastName>Goodman</lastName>
        <id>n101937c</id>
    </student>
	<student>
        <firstName>Landin</firstName>
        <lastName>Bender</lastName>
        <id>n109829c</id>
    </student>
	<student>
        <firstName>Dahlia</firstName>
        <lastName>Christensen</lastName>
        <id>n109025c</id>
    </student>
	<student>
        <firstName>Urijah</firstName>
        <lastName>Marks</lastName>
        <id>n105178c</id>
    </student>
	<student>
        <firstName>Eliana</firstName>
        <lastName>Bullock</lastName>
        <id>n102694c</id>
    </student>
	<student>
        <firstName>Alejandro</firstName>
        <lastName>Alejandro</lastName>
        <id>n107742c</id>
    </student>
	<student>
        <firstName>Addison</firstName>
        <lastName>Glass</lastName>
        <id>n107099c</id>
    </student>
	<student>
        <firstName>Fisher</firstName>
        <lastName>Dodson</lastName>
        <id>n100562c</id>
    </student>
	<student>
        <firstName>Ethen</firstName>
        <lastName>Mathis</lastName>
        <id>n100784c</id>
    </student>
	<student>
        <firstName>Makai</firstName>
        <lastName>Cannon</lastName>
        <id>n100355c</id>
    </student>
	<student>
        <firstName>Landyn</firstName>
        <lastName>Velez</lastName>
        <id>n102347c</id>
    </student>
	<student>
        <firstName>Sloane</firstName>
        <lastName>Campbell</lastName>
        <id>n105327c</id>
    </student>
</courseRoster>